pmmutils/__init__.py
pmmutils/args.py
pmmutils/exceptions.py
pmmutils/logging.py
pmmutils/schedule.py
pmmutils/util.py
pmmutils/yaml.py
pmmutils-0.5.10.dist-info/LICENSE
pmmutils-0.5.10.dist-info/METADATA
pmmutils-0.5.10.dist-info/WHEEL
pmmutils-0.5.10.dist-info/top_level.txt
pmmutils-0.5.10.dist-info/RECORD
