Metadata-Version: 2.1
Name: pmmutils
Version: 0.5.10
Summary: Util Methods for PMM
Home-page: https://github.com/meisnate12/pmmutils
Author: Nathan Taggart
Author-email: meisnate12@gmail.com
License: MIT License
Project-URL: Documentation, https://github.com/meisnate12/pmmutils
Project-URL: Funding, https://github.com/sponsors/meisnate12
Project-URL: Source, https://github.com/meisnate12/pmmutils
Project-URL: Issues, https://github.com/meisnate12/pmmutils/issues
Keywords: pmmutils
Classifier: Development Status :: 5 - Production/Stable
Classifier: Intended Audience :: Developers
Classifier: Topic :: Software Development :: Libraries
Classifier: Programming Language :: Python
Classifier: Programming Language :: Python :: 3.11
Classifier: Programming Language :: Python :: 3.12
Requires-Python: >=3.11
License-File: LICENSE
Requires-Dist: GitPython >=3.1.40
Requires-Dist: pathvalidate >=3.2.0
Requires-Dist: psutil >=5.9.7
Requires-Dist: python-dotenv >=1.0.0
Requires-Dist: requests >=2.31.0
Requires-Dist: ruamel.yaml >=0.18.5
Requires-Dist: tqdm >=4.66.1
Requires-Dist: setuptools >=69.0.3
